mloda/registry/__init__.py
mloda_registry-0.2.6.dist-info/METADATA
mloda_registry-0.2.6.dist-info/WHEEL
mloda_registry-0.2.6.dist-info/top_level.txt
mloda_registry-0.2.6.dist-info/RECORD
