Metadata-Version: 2.4
Name: mloda-registry
Version: 0.2.6
Summary: Plugin discovery and search for mloda
Author-email: Tom Kaltofen <info@mloda.ai>
License-Expression: Apache-2.0
Project-URL: Homepage, https://mloda.ai
Project-URL: Repository, https://github.com/mloda-ai/mloda-registry
Requires-Python: >=3.10
Requires-Dist: mloda>=0.4.3
Provides-Extra: dev
Requires-Dist: mloda-testing; extra == "dev"
Requires-Dist: pytest; extra == "dev"
